odoo/addons/sale_coupon_product_exclude/README.rst
odoo/addons/sale_coupon_product_exclude/__init__.py
odoo/addons/sale_coupon_product_exclude/__manifest__.py
odoo/addons/sale_coupon_product_exclude/i18n/it.po
odoo/addons/sale_coupon_product_exclude/i18n/sale_coupon_product_exclude.pot
odoo/addons/sale_coupon_product_exclude/models/__init__.py
odoo/addons/sale_coupon_product_exclude/models/coupon_program.py
odoo/addons/sale_coupon_product_exclude/models/coupon_reward.py
odoo/addons/sale_coupon_product_exclude/models/sale_order.py
odoo/addons/sale_coupon_product_exclude/readme/CONTRIBUTORS.rst
odoo/addons/sale_coupon_product_exclude/readme/DESCRIPTION.rst
odoo/addons/sale_coupon_product_exclude/readme/USAGE.rst
odoo/addons/sale_coupon_product_exclude/static/description/icon.png
odoo/addons/sale_coupon_product_exclude/static/description/index.html
odoo/addons/sale_coupon_product_exclude/tests/__init__.py
odoo/addons/sale_coupon_product_exclude/tests/test_sale_coupon_product_exclude.py
odoo/addons/sale_coupon_product_exclude/views/coupon_program_views.xml
odoo14_addon_sale_coupon_product_exclude-14.0.1.0.1.dev6.dist-info/METADATA
odoo14_addon_sale_coupon_product_exclude-14.0.1.0.1.dev6.dist-info/WHEEL
odoo14_addon_sale_coupon_product_exclude-14.0.1.0.1.dev6.dist-info/top_level.txt
odoo14_addon_sale_coupon_product_exclude-14.0.1.0.1.dev6.dist-info/RECORD
